inkslab/__init__.py
inkslab/bx.py
inkslab/conv_mtx_idx.py
inkslab/g_pts.py
inkslab/g_pts_1d.py
inkslab/im.py
inkslab/layer.py
inkslab/layer_copy.py
inkslab/max_idx_diff.py
inkslab/mtr.py
inkslab/params.py
inkslab/recipro.py
inkslab/rsp.py
inkslab/shps.py
inkslab/simulator.py
inkslab/sm.py
inkslab/ft/__init__.py
inkslab/ft/ft_1d_sq.py
inkslab/ft/ft_2d_cnst.py
inkslab/ft/ft_2d_disk.py
inkslab/ft/ft_2d_ellip.py
inkslab/ft/ft_2d_para.py
inkslab/ft/ft_2d_poly.py
inkslab/ft/ft_2d_rct.py
inkslab/ft/gibbs.py
inkslab/ft/poly_area.py
inkslab/helpers/__init__.py
inkslab/helpers/pt_in_poly.py
inkslab-0.1.0.dist-info/LICENSE
inkslab-0.1.0.dist-info/METADATA
inkslab-0.1.0.dist-info/WHEEL
inkslab-0.1.0.dist-info/top_level.txt
inkslab-0.1.0.dist-info/RECORD
