Metadata-Version: 2.1
Name: inkslab
Version: 0.1.0
Summary: 3D efficient solver for multi-stacked in-plane periodic structures using rcwa.
Home-page: https://github.com/alexysong/inkslab
Author: Alex Y. Song
Author-email: song.alexy@gmail.com
License: UNKNOWN
Keywords: rcwa
Platform: UNKNOWN
Classifier: Programming Language :: Python :: 3
Classifier: Topic :: Scientific/Engineering
Classifier: License :: OSI Approved :: GNU Affero General Public License v3 or later (AGPLv3+)
Requires-Dist: numpy (>=1.11.3)
Requires-Dist: scipy
